pytest_archon/__init__.py
pytest_archon/collect.py
pytest_archon/core_modules.py
pytest_archon/failure.py
pytest_archon/plugin.py
pytest_archon/py.typed
pytest_archon/rule.py
pytest_archon/assets/core-module-lists/3.6.txt
pytest_archon/assets/core-module-lists/3.7.txt
pytest_archon/assets/core-module-lists/3.8.txt
pytest_archon/assets/core-module-lists/3.9.txt
pytest_archon-0.0.7.dist-info/licenses/LICENSE
pytest_archon-0.0.7.dist-info/METADATA
pytest_archon-0.0.7.dist-info/WHEEL
pytest_archon-0.0.7.dist-info/entry_points.txt
pytest_archon-0.0.7.dist-info/top_level.txt
pytest_archon-0.0.7.dist-info/RECORD
