Metadata-Version: 2.4
Name: pytest-archon
Version: 0.0.7
Summary: Rule your architecture like a real developer
Author-email: Arjan Molenaar <gaphor@gmail.com>, Joachim Bargsten <jw@bargsten.org>
License: Apache Software License
Project-URL: homepage, https://github.com/jwbargsten/pytest-archon
Project-URL: repository, https://github.com/jwbargsten/pytest-archon
Classifier: Programming Language :: Python :: 3
Classifier: Programming Language :: Python :: 3.8
Classifier: Programming Language :: Python :: 3.9
Classifier: Programming Language :: Python :: 3.10
Classifier: Programming Language :: Python :: 3.11
Classifier: License :: OSI Approved :: Apache Software License
Classifier: Framework :: Pytest
Classifier: Development Status :: 5 - Production/Stable
Requires-Python: >=3.8
License-File: LICENSE
Requires-Dist: pytest>=7.2
Provides-Extra: dev
Requires-Dist: coverage; extra == "dev"
Requires-Dist: ruff; extra == "dev"
Requires-Dist: mypy; extra == "dev"
Requires-Dist: check-manifest; extra == "dev"
Requires-Dist: check-wheel-contents; extra == "dev"
Requires-Dist: pyroma; extra == "dev"
Dynamic: license-file
